[
  {
    "version": "3.13.1",
    "stable": true,
    "release_url": "https://github.com/priya-kinthali/python-versions/releases/tag/3.13.1-12632461963",
    "files": [
      {
        "filename": "python-3.13.1-linux-22.04-x64-freethreaded.tar.gz",
        "arch": "x64-freethreaded",
        "platform": "linux",
        "platform_version": "22.04",
        "download_url": "https://github.com/priya-kinthali/python-versions/releases/download/3.13.1-12632461963/python-3.13.1-linux-22.04-x64-freethreaded.tar.gz"
      }
    ]
  },
  {
    "version": "3.13.0",
    "stable": true,
    "release_url": "https://github.com/priya-kinthali/python-versions/releases/tag/3.13.0-12629498138",
    "files": [
      {
        "filename": "python-3.13.0-linux-22.04-x64-freethreaded.tar.gz",
        "arch": "x64-freethreaded",
        "platform": "linux",
        "platform_version": "22.04",
        "download_url": "https://github.com/priya-kinthali/python-versions/releases/download/3.13.0-12629498138/python-3.13.0-linux-22.04-x64-freethreaded.tar.gz"
      }
    ]
  }
]
